[
  {
    "id": 2377180750,
    "pid": 158317561,
    "tid": null,
    "uid": 5298429,
    "description": "Toggl",
    "start": "2022-02-19T17:36:44+01:00",
    "end": "2022-02-19T19:13:54+01:00",
    "updated": "2022-02-19T19:13:55+01:00",
    "dur": 5830000,
    "user": "Huy",
    "use_stop": true,
    "client": "Fun & Future",
    "project": "Coding Projects",
    "project_color": "0",
    "project_hex_color": "#e36a00",
    "task": null,
    "billable": null,
    "is_billable": false,
    "cur": null,
    "tags": []
  },
  {
    "id": 2377172046,
    "pid": 176309267,
    "tid": null,
    "uid": 5298429,
    "description": "Break",
    "start": "2022-02-19T17:12:11+01:00",
    "end": "2022-02-19T17:36:44+01:00",
    "updated": "2022-02-19T17:36:47+01:00",
    "dur": 1473000,
    "user": "Huy",
    "use_stop": true,
    "client": "Future",
    "project": "Necessary",
    "project_color": "0",
    "project_hex_color": "#0b83d9",
    "task": null,
    "billable": null,
    "is_billable": false,
    "cur": null,
    "tags": []
  },
  {
    "id": 2377157688,
    "pid": 158317561,
    "tid": null,
    "uid": 5298429,
    "description": "Toggl",
    "start": "2022-02-19T16:29:52+01:00",
    "end": "2022-02-19T17:12:10+01:00",
    "updated": "2022-02-19T17:12:12+01:00",
    "dur": 2538000,
    "user": "Huy",
    "use_stop": true,
    "client": "Fun & Future",
    "project": "Coding Projects",
    "project_color": "0",
    "project_hex_color": "#e36a00",
    "task": null,
    "billable": null,
    "is_billable": false,
    "cur": null,
    "tags": []
  },
  {
    "id": 2377154141,
    "pid": 176309267,
    "tid": null,
    "uid": 5298429,
    "description": "Organizing",
    "start": "2022-02-19T16:18:47+01:00",
    "end": "2022-02-19T16:29:52+01:00",
    "updated": "2022-02-19T16:29:53+01:00",
    "dur": 665000,
    "user": "Huy",
    "use_stop": true,
    "client": "Future",
    "project": "Necessary",
    "project_color": "0",
    "project_hex_color": "#0b83d9",
    "task": null,
    "billable": null,
    "is_billable": false,
    "cur": null,
    "tags": []
  },
  {
    "id": 2377153989,
    "pid": 176309267,
    "tid": null,
    "uid": 5298429,
    "description": "Organizing",
    "start": "2022-02-19T16:00:00+01:00",
    "end": "2022-02-19T16:18:43+01:00",
    "updated": "2022-02-19T16:18:44+01:00",
    "dur": 1123000,
    "user": "Huy",
    "use_stop": true,
    "client": "Future",
    "project": "Necessary",
    "project_color": "0",
    "project_hex_color": "#0b83d9",
    "task": null,
    "billable": null,
    "is_billable": false,
    "cur": null,
    "tags": []
  },
  {
    "id": 2377133435,
    "pid": 176309267,
    "tid": null,
    "uid": 5298429,
    "description": "Cooking & Eating",
    "start": "2022-02-19T15:17:33+01:00",
    "end": "2022-02-19T16:00:00+01:00",
    "updated": "2022-02-19T16:18:37+01:00",
    "dur": 2547000,
    "user": "Huy",
    "use_stop": true,
    "client": "Future",
    "project": "Necessary",
    "project_color": "0",
    "project_hex_color": "#0b83d9",
    "task": null,
    "billable": null,
    "is_billable": false,
    "cur": null,
    "tags": []
  },
  {
    "id": 2377110091,
    "pid": 176309267,
    "tid": null,
    "uid": 5298429,
    "description": "Organizing",
    "start": "2022-02-19T14:03:03+01:00",
    "end": "2022-02-19T15:17:33+01:00",
    "updated": "2022-02-19T15:17:35+01:00",
    "dur": 4470000,
    "user": "Huy",
    "use_stop": true,
    "client": "Future",
    "project": "Necessary",
    "project_color": "0",
    "project_hex_color": "#0b83d9",
    "task": null,
    "billable": null,
    "is_billable": false,
    "cur": null,
    "tags": []
  },
  {
    "id": 2377083216,
    "pid": 158317561,
    "tid": null,
    "uid": 5298429,
    "description": "Toggl",
    "start": "2022-02-19T12:28:09+01:00",
    "end": "2022-02-19T14:02:59+01:00",
    "updated": "2022-02-19T14:03:00+01:00",
    "dur": 5690000,
    "user": "Huy",
    "use_stop": true,
    "client": "Fun & Future",
    "project": "Coding Projects",
    "project_color": "0",
    "project_hex_color": "#e36a00",
    "task": null,
    "billable": null,
    "is_billable": false,
    "cur": null,
    "tags": []
  },
  {
    "id": 2377049724,
    "pid": 177268557,
    "tid": null,
    "uid": 5298429,
    "description": "Relax",
    "start": "2022-02-19T10:03:02+01:00",
    "end": "2022-02-19T12:28:07+01:00",
    "updated": "2022-02-19T12:28:08+01:00",
    "dur": 8705000,
    "user": "Huy",
    "use_stop": true,
    "client": "Fun",
    "project": "Feel Comfortable",
    "project_color": "0",
    "project_hex_color": "#9e5bd9",
    "task": null,
    "billable": null,
    "is_billable": false,
    "cur": null,
    "tags": []
  },
  {
    "id": 2377044760,
    "pid": 176309103,
    "tid": null,
    "uid": 5298429,
    "description": "Sleep",
    "start": "2022-02-19T01:30:00+01:00",
    "end": "2022-02-19T10:03:01+01:00",
    "updated": "2022-02-19T10:03:02+01:00",
    "dur": 30781000,
    "user": "Huy",
    "use_stop": true,
    "client": "Sleep",
    "project": "Sleep",
    "project_color": "0",
    "project_hex_color": "#525266",
    "task": null,
    "billable": null,
    "is_billable": false,
    "cur": null,
    "tags": []
  },
  {
    "id": 2376720208,
    "pid": 177268557,
    "tid": null,
    "uid": 5298429,
    "description": "Relax",
    "start": "2022-02-18T20:30:00+01:00",
    "end": "2022-02-19T01:30:00+01:00",
    "updated": "2022-02-19T10:02:59+01:00",
    "dur": 18000000,
    "user": "Huy",
    "use_stop": true,
    "client": "Fun",
    "project": "Feel Comfortable",
    "project_color": "0",
    "project_hex_color": "#9e5bd9",
    "task": null,
    "billable": null,
    "is_billable": false,
    "cur": null,
    "tags": []
  },
  {
    "id": 2376670517,
    "pid": 176654174,
    "tid": null,
    "uid": 5298429,
    "description": "Coding Video",
    "start": "2022-02-18T20:16:45+01:00",
    "end": "2022-02-18T20:30:00+01:00",
    "updated": "2022-02-18T21:01:41+01:00",
    "dur": 795000,
    "user": "Huy",
    "use_stop": true,
    "client": "Fun & Future",
    "project": "Education",
    "project_color": "0",
    "project_hex_color": "#990099",
    "task": null,
    "billable": null,
    "is_billable": false,
    "cur": null,
    "tags": []
  },
  {
    "id": 2376477179,
    "pid": 177268557,
    "tid": null,
    "uid": 5298429,
    "description": "Relax",
    "start": "2022-02-18T17:53:12+01:00",
    "end": "2022-02-18T20:16:44+01:00",
    "updated": "2022-02-18T20:16:45+01:00",
    "dur": 8612000,
    "user": "Huy",
    "use_stop": true,
    "client": "Fun",
    "project": "Feel Comfortable",
    "project_color": "0",
    "project_hex_color": "#9e5bd9",
    "task": null,
    "billable": null,
    "is_billable": false,
    "cur": null,
    "tags": []
  },
  {
    "id": 2376366033,
    "pid": 176309267,
    "tid": null,
    "uid": 5298429,
    "description": "Cooking & Eating",
    "start": "2022-02-18T16:48:05+01:00",
    "end": "2022-02-18T17:53:12+01:00",
    "updated": "2022-02-18T17:53:14+01:00",
    "dur": 3907000,
    "user": "Huy",
    "use_stop": true,
    "client": "Future",
    "project": "Necessary",
    "project_color": "0",
    "project_hex_color": "#0b83d9",
    "task": null,
    "billable": null,
    "is_billable": false,
    "cur": null,
    "tags": []
  },
  {
    "id": 2376341345,
    "pid": 176309267,
    "tid": null,
    "uid": 5298429,
    "description": "Break",
    "start": "2022-02-18T16:33:34+01:00",
    "end": "2022-02-18T16:48:05+01:00",
    "updated": "2022-02-18T16:48:07+01:00",
    "dur": 871000,
    "user": "Huy",
    "use_stop": true,
    "client": "Future",
    "project": "Necessary",
    "project_color": "0",
    "project_hex_color": "#0b83d9",
    "task": null,
    "billable": null,
    "is_billable": false,
    "cur": null,
    "tags": []
  },
  {
    "id": 2376269977,
    "pid": 158317561,
    "tid": null,
    "uid": 5298429,
    "description": "Toggl",
    "start": "2022-02-18T15:55:08+01:00",
    "end": "2022-02-18T16:33:32+01:00",
    "updated": "2022-02-18T16:33:33+01:00",
    "dur": 2304000,
    "user": "Huy",
    "use_stop": true,
    "client": "Fun & Future",
    "project": "Coding Projects",
    "project_color": "0",
    "project_hex_color": "#e36a00",
    "task": null,
    "billable": null,
    "is_billable": false,
    "cur": null,
    "tags": []
  },
  {
    "id": 2376215441,
    "pid": 176309267,
    "tid": null,
    "uid": 5298429,
    "description": "Break",
    "start": "2022-02-18T15:25:14+01:00",
    "end": "2022-02-18T15:54:47+01:00",
    "updated": "2022-02-18T15:54:49+01:00",
    "dur": 1773000,
    "user": "Huy",
    "use_stop": true,
    "client": "Future",
    "project": "Necessary",
    "project_color": "0",
    "project_hex_color": "#0b83d9",
    "task": null,
    "billable": null,
    "is_billable": false,
    "cur": null,
    "tags": []
  },
  {
    "id": 2376117654,
    "pid": 158317561,
    "tid": null,
    "uid": 5298429,
    "description": "Toggl",
    "start": "2022-02-18T14:30:31+01:00",
    "end": "2022-02-18T15:24:59+01:00",
    "updated": "2022-02-18T15:25:01+01:00",
    "dur": 3268000,
    "user": "Huy",
    "use_stop": true,
    "client": "Fun & Future",
    "project": "Coding Projects",
    "project_color": "0",
    "project_hex_color": "#e36a00",
    "task": null,
    "billable": null,
    "is_billable": false,
    "cur": null,
    "tags": []
  },
  {
    "id": 2376103360,
    "pid": 176309267,
    "tid": null,
    "uid": 5298429,
    "description": "Organizing",
    "start": "2022-02-18T14:21:51+01:00",
    "end": "2022-02-18T14:30:24+01:00",
    "updated": "2022-02-18T14:30:25+01:00",
    "dur": 513000,
    "user": "Huy",
    "use_stop": true,
    "client": "Future",
    "project": "Necessary",
    "project_color": "0",
    "project_hex_color": "#0b83d9",
    "task": null,
    "billable": null,
    "is_billable": false,
    "cur": null,
    "tags": []
  },
  {
    "id": 2375915294,
    "pid": 177268557,
    "tid": null,
    "uid": 5298429,
    "description": "Relax",
    "start": "2022-02-18T11:45:00+01:00",
    "end": "2022-02-18T14:21:46+01:00",
    "updated": "2022-02-18T14:21:48+01:00",
    "dur": 9406000,
    "user": "Huy",
    "use_stop": true,
    "client": "Fun",
    "project": "Feel Comfortable",
    "project_color": "0",
    "project_hex_color": "#9e5bd9",
    "task": null,
    "billable": null,
    "is_billable": false,
    "cur": null,
    "tags": []
  },
  {
    "id": 2375835544,
    "pid": 176309267,
    "tid": null,
    "uid": 5298429,
    "description": "Cooking & Eating",
    "start": "2022-02-18T11:17:44+01:00",
    "end": "2022-02-18T11:45:00+01:00",
    "updated": "2022-02-18T12:13:07+01:00",
    "dur": 1636000,
    "user": "Huy",
    "use_stop": true,
    "client": "Future",
    "project": "Necessary",
    "project_color": "0",
    "project_hex_color": "#0b83d9",
    "task": null,
    "billable": null,
    "is_billable": false,
    "cur": null,
    "tags": []
  },
  {
    "id": 2375792626,
    "pid": 176309267,
    "tid": null,
    "uid": 5298429,
    "description": "Morning Routine",
    "start": "2022-02-18T10:49:37+01:00",
    "end": "2022-02-18T11:17:43+01:00",
    "updated": "2022-02-18T11:17:43+01:00",
    "dur": 1686000,
    "user": "Huy",
    "use_stop": true,
    "client": "Future",
    "project": "Necessary",
    "project_color": "0",
    "project_hex_color": "#0b83d9",
    "task": null,
    "billable": null,
    "is_billable": false,
    "cur": null,
    "tags": []
  },
  {
    "id": 2375725742,
    "pid": 177268557,
    "tid": null,
    "uid": 5298429,
    "description": "Relax",
    "start": "2022-02-18T10:05:46+01:00",
    "end": "2022-02-18T10:49:36+01:00",
    "updated": "2022-02-18T10:49:37+01:00",
    "dur": 2630000,
    "user": "Huy",
    "use_stop": true,
    "client": "Fun",
    "project": "Feel Comfortable",
    "project_color": "0",
    "project_hex_color": "#9e5bd9",
    "task": null,
    "billable": null,
    "is_billable": false,
    "cur": null,
    "tags": []
  },
  {
    "id": 2375725074,
    "pid": 176309103,
    "tid": null,
    "uid": 5298429,
    "description": "Sleep",
    "start": "2022-02-18T01:30:00+01:00",
    "end": "2022-02-18T10:05:46+01:00",
    "updated": "2022-02-18T10:05:46+01:00",
    "dur": 30946000,
    "user": "Huy",
    "use_stop": true,
    "client": "Sleep",
    "project": "Sleep",
    "project_color": "0",
    "project_hex_color": "#525266",
    "task": null,
    "billable": null,
    "is_billable": false,
    "cur": null,
    "tags": []
  },
  {
    "id": 2375188070,
    "pid": 177268557,
    "tid": null,
    "uid": 5298429,
    "description": "Relax",
    "start": "2022-02-17T23:05:15+01:00",
    "end": "2022-02-18T01:30:00+01:00",
    "updated": "2022-02-18T10:05:32+01:00",
    "dur": 8685000,
    "user": "Huy",
    "use_stop": true,
    "client": "Fun",
    "project": "Feel Comfortable",
    "project_color": "0",
    "project_hex_color": "#9e5bd9",
    "task": null,
    "billable": null,
    "is_billable": false,
    "cur": null,
    "tags": []
  },
  {
    "id": 2375187904,
    "pid": 176309267,
    "tid": null,
    "uid": 5298429,
    "description": "Cooking & Eating",
    "start": "2022-02-17T22:15:00+01:00",
    "end": "2022-02-17T23:05:14+01:00",
    "updated": "2022-02-17T23:05:14+01:00",
    "dur": 3014000,
    "user": "Huy",
    "use_stop": true,
    "client": "Future",
    "project": "Necessary",
    "project_color": "0",
    "project_hex_color": "#0b83d9",
    "task": null,
    "billable": null,
    "is_billable": false,
    "cur": null,
    "tags": []
  },
  {
    "id": 2374966740,
    "pid": 177005400,
    "tid": null,
    "uid": 5298429,
    "description": "Bouldering",
    "start": "2022-02-17T20:11:49+01:00",
    "end": "2022-02-17T22:15:00+01:00",
    "updated": "2022-02-17T23:05:14+01:00",
    "dur": 7391000,
    "user": "Huy",
    "use_stop": true,
    "client": "Fun",
    "project": "Exercise",
    "project_color": "0",
    "project_hex_color": "#c7af14",
    "task": null,
    "billable": null,
    "is_billable": false,
    "cur": null,
    "tags": []
  },
  {
    "id": 2374902148,
    "pid": 158317561,
    "tid": null,
    "uid": 5298429,
    "description": "Scripting",
    "start": "2022-02-17T19:27:39+01:00",
    "end": "2022-02-17T20:11:46+01:00",
    "updated": "2022-02-17T20:11:47+01:00",
    "dur": 2647000,
    "user": "Huy",
    "use_stop": true,
    "client": "Fun & Future",
    "project": "Coding Projects",
    "project_color": "0",
    "project_hex_color": "#e36a00",
    "task": null,
    "billable": null,
    "is_billable": false,
    "cur": null,
    "tags": []
  },
  {
    "id": 2374883153,
    "pid": 176356870,
    "tid": null,
    "uid": 5298429,
    "description": "ADHD education",
    "start": "2022-02-17T19:13:38+01:00",
    "end": "2022-02-17T19:27:26+01:00",
    "updated": "2022-02-17T19:27:27+01:00",
    "dur": 828000,
    "user": "Huy",
    "use_stop": true,
    "client": "Fun",
    "project": "Health",
    "project_color": "0",
    "project_hex_color": "#c7af14",
    "task": null,
    "billable": null,
    "is_billable": false,
    "cur": null,
    "tags": []
  },
  {
    "id": 2374813709,
    "pid": 177268557,
    "tid": null,
    "uid": 5298429,
    "description": "Relax",
    "start": "2022-02-17T18:30:19+01:00",
    "end": "2022-02-17T19:13:38+01:00",
    "updated": "2022-02-17T19:13:38+01:00",
    "dur": 2599000,
    "user": "Huy",
    "use_stop": true,
    "client": "Fun",
    "project": "Feel Comfortable",
    "project_color": "0",
    "project_hex_color": "#9e5bd9",
    "task": null,
    "billable": null,
    "is_billable": false,
    "cur": null,
    "tags": []
  },
  {
    "id": 2374813289,
    "pid": 176309267,
    "tid": null,
    "uid": 5298429,
    "description": "Organizing",
    "start": "2022-02-17T18:00:00+01:00",
    "end": "2022-02-17T18:30:17+01:00",
    "updated": "2022-02-17T18:30:18+01:00",
    "dur": 1817000,
    "user": "Huy",
    "use_stop": true,
    "client": "Future",
    "project": "Necessary",
    "project_color": "0",
    "project_hex_color": "#0b83d9",
    "task": null,
    "billable": null,
    "is_billable": false,
    "cur": null,
    "tags": []
  },
  {
    "id": 2374702938,
    "pid": 177268557,
    "tid": null,
    "uid": 5298429,
    "description": "Relax",
    "start": "2022-02-17T17:29:14+01:00",
    "end": "2022-02-17T18:00:00+01:00",
    "updated": "2022-02-17T18:30:16+01:00",
    "dur": 1846000,
    "user": "Huy",
    "use_stop": true,
    "client": "Fun",
    "project": "Feel Comfortable",
    "project_color": "0",
    "project_hex_color": "#9e5bd9",
    "task": null,
    "billable": null,
    "is_billable": false,
    "cur": null,
    "tags": []
  },
  {
    "id": 2374538739,
    "pid": 176309267,
    "tid": null,
    "uid": 5298429,
    "description": "Organizing",
    "start": "2022-02-17T16:07:50+01:00",
    "end": "2022-02-17T17:29:14+01:00",
    "updated": "2022-02-17T17:29:14+01:00",
    "dur": 4884000,
    "user": "Huy",
    "use_stop": true,
    "client": "Future",
    "project": "Necessary",
    "project_color": "0",
    "project_hex_color": "#0b83d9",
    "task": null,
    "billable": null,
    "is_billable": false,
    "cur": null,
    "tags": []
  },
  {
    "id": 2374186998,
    "pid": 176309651,
    "tid": null,
    "uid": 5298429,
    "description": "Laura",
    "start": "2022-02-17T09:45:00+01:00",
    "end": "2022-02-17T16:07:48+01:00",
    "updated": "2022-02-17T16:07:51+01:00",
    "dur": 22968000,
    "user": "Huy",
    "use_stop": true,
    "client": "Fun",
    "project": "Relationships",
    "project_color": "0",
    "project_hex_color": "#d94182",
    "task": null,
    "billable": null,
    "is_billable": false,
    "cur": null,
    "tags": []
  },
  {
    "id": 2374186394,
    "pid": 176309103,
    "tid": null,
    "uid": 5298429,
    "description": "Sleep",
    "start": "2022-02-17T01:00:00+01:00",
    "end": "2022-02-17T09:45:00+01:00",
    "updated": "2022-02-17T13:02:10+01:00",
    "dur": 31500000,
    "user": "Huy",
    "use_stop": true,
    "client": "Sleep",
    "project": "Sleep",
    "project_color": "0",
    "project_hex_color": "#525266",
    "task": null,
    "billable": null,
    "is_billable": false,
    "cur": null,
    "tags": []
  },
  {
    "id": 2373270604,
    "pid": 176309651,
    "tid": null,
    "uid": 5298429,
    "description": "Laura",
    "start": "2022-02-16T22:19:41+01:00",
    "end": "2022-02-17T01:00:00+01:00",
    "updated": "2022-02-17T13:01:49+01:00",
    "dur": 9619000,
    "user": "Huy",
    "use_stop": true,
    "client": "Fun",
    "project": "Relationships",
    "project_color": "0",
    "project_hex_color": "#d94182",
    "task": null,
    "billable": null,
    "is_billable": false,
    "cur": null,
    "tags": []
  },
  {
    "id": 2373017976,
    "pid": 176309267,
    "tid": null,
    "uid": 5298429,
    "description": "Cooking & Eating",
    "start": "2022-02-16T19:19:28+01:00",
    "end": "2022-02-16T22:19:41+01:00",
    "updated": "2022-02-16T22:19:42+01:00",
    "dur": 10813000,
    "user": "Huy",
    "use_stop": true,
    "client": "Future",
    "project": "Necessary",
    "project_color": "0",
    "project_hex_color": "#0b83d9",
    "task": null,
    "billable": null,
    "is_billable": false,
    "cur": null,
    "tags": []
  },
  {
    "id": 2373003762,
    "pid": 176309651,
    "tid": null,
    "uid": 5298429,
    "description": "Laura",
    "start": "2022-02-16T17:00:00+01:00",
    "end": "2022-02-16T19:19:27+01:00",
    "updated": "2022-02-16T19:19:28+01:00",
    "dur": 8367000,
    "user": "Huy",
    "use_stop": true,
    "client": "Fun",
    "project": "Relationships",
    "project_color": "0",
    "project_hex_color": "#d94182",
    "task": null,
    "billable": null,
    "is_billable": false,
    "cur": null,
    "tags": []
  },
  {
    "id": 2372655647,
    "pid": 177005400,
    "tid": null,
    "uid": 5298429,
    "description": "Bouldering",
    "start": "2022-02-16T16:09:55+01:00",
    "end": "2022-02-16T17:00:00+01:00",
    "updated": "2022-02-16T19:10:14+01:00",
    "dur": 3005000,
    "user": "Huy",
    "use_stop": true,
    "client": "Fun",
    "project": "Exercise",
    "project_color": "0",
    "project_hex_color": "#c7af14",
    "task": null,
    "billable": null,
    "is_billable": false,
    "cur": null,
    "tags": []
  },
  {
    "id": 2372579881,
    "pid": 177268557,
    "tid": null,
    "uid": 5298429,
    "description": "Relax",
    "start": "2022-02-16T15:35:57+01:00",
    "end": "2022-02-16T16:09:51+01:00",
    "updated": "2022-02-16T16:10:02+01:00",
    "dur": 2034000,
    "user": "Huy",
    "use_stop": true,
    "client": "Fun",
    "project": "Feel Comfortable",
    "project_color": "0",
    "project_hex_color": "#9e5bd9",
    "task": null,
    "billable": null,
    "is_billable": false,
    "cur": null,
    "tags": []
  },
  {
    "id": 2372424240,
    "pid": 176309267,
    "tid": null,
    "uid": 5298429,
    "description": "Organizing",
    "start": "2022-02-16T14:20:21+01:00",
    "end": "2022-02-16T15:35:52+01:00",
    "updated": "2022-02-16T15:35:56+01:00",
    "dur": 4531000,
    "user": "Huy",
    "use_stop": true,
    "client": "Future",
    "project": "Necessary",
    "project_color": "0",
    "project_hex_color": "#0b83d9",
    "task": null,
    "billable": null,
    "is_billable": false,
    "cur": null,
    "tags": []
  },
  {
    "id": 2372330860,
    "pid": 176309267,
    "tid": null,
    "uid": 5298429,
    "description": "Cooking & Eating",
    "start": "2022-02-16T13:27:11+01:00",
    "end": "2022-02-16T14:20:20+01:00",
    "updated": "2022-02-16T14:20:24+01:00",
    "dur": 3189000,
    "user": "Huy",
    "use_stop": true,
    "client": "Future",
    "project": "Necessary",
    "project_color": "0",
    "project_hex_color": "#0b83d9",
    "task": null,
    "billable": null,
    "is_billable": false,
    "cur": null,
    "tags": []
  },
  {
    "id": 2372021626,
    "pid": 176356870,
    "tid": null,
    "uid": 5298429,
    "description": "Doctor",
    "start": "2022-02-16T10:14:41+01:00",
    "end": "2022-02-16T13:27:09+01:00",
    "updated": "2022-02-16T13:27:10+01:00",
    "dur": 11548000,
    "user": "Huy",
    "use_stop": true,
    "client": "Fun",
    "project": "Health",
    "project_color": "0",
    "project_hex_color": "#c7af14",
    "task": null,
    "billable": null,
    "is_billable": false,
    "cur": null,
    "tags": []
  },
  {
    "id": 2371946948,
    "pid": 177268557,
    "tid": null,
    "uid": 5298429,
    "description": "Relax",
    "start": "2022-02-16T09:31:49+01:00",
    "end": "2022-02-16T10:14:41+01:00",
    "updated": "2022-02-16T10:14:41+01:00",
    "dur": 2572000,
    "user": "Huy",
    "use_stop": true,
    "client": "Fun",
    "project": "Feel Comfortable",
    "project_color": "0",
    "project_hex_color": "#9e5bd9",
    "task": null,
    "billable": null,
    "is_billable": false,
    "cur": null,
    "tags": []
  },
  {
    "id": 2371946524,
    "pid": 176309267,
    "tid": null,
    "uid": 5298429,
    "description": "Morning Routine",
    "start": "2022-02-16T08:30:00+01:00",
    "end": "2022-02-16T09:31:48+01:00",
    "updated": "2022-02-16T09:31:49+01:00",
    "dur": 3708000,
    "user": "Huy",
    "use_stop": true,
    "client": "Future",
    "project": "Necessary",
    "project_color": "0",
    "project_hex_color": "#0b83d9",
    "task": null,
    "billable": null,
    "is_billable": false,
    "cur": null,
    "tags": []
  },
  {
    "id": 2371946484,
    "pid": 176309103,
    "tid": null,
    "uid": 5298429,
    "description": "Sleep",
    "start": "2022-02-16T00:08:58+01:00",
    "end": "2022-02-16T08:30:00+01:00",
    "updated": "2022-02-16T09:31:42+01:00",
    "dur": 30062000,
    "user": "Huy",
    "use_stop": true,
    "client": "Sleep",
    "project": "Sleep",
    "project_color": "0",
    "project_hex_color": "#525266",
    "task": null,
    "billable": null,
    "is_billable": false,
    "cur": null,
    "tags": []
  },
  {
    "id": 2371040871,
    "pid": 176309651,
    "tid": null,
    "uid": 5298429,
    "description": "Laura",
    "start": "2022-02-15T18:48:32+01:00",
    "end": "2022-02-16T00:08:56+01:00",
    "updated": "2022-02-16T00:08:57+01:00",
    "dur": 19224000,
    "user": "Huy",
    "use_stop": true,
    "client": "Fun",
    "project": "Relationships",
    "project_color": "0",
    "project_hex_color": "#d94182",
    "task": null,
    "billable": null,
    "is_billable": false,
    "cur": null,
    "tags": []
  },
  {
    "id": 2370929060,
    "pid": 158317561,
    "tid": null,
    "uid": 5298429,
    "description": "Scripting",
    "start": "2022-02-15T17:46:39+01:00",
    "end": "2022-02-15T18:48:32+01:00",
    "updated": "2022-02-15T18:48:33+01:00",
    "dur": 3713000,
    "user": "Huy",
    "use_stop": true,
    "client": "Fun & Future",
    "project": "Coding Projects",
    "project_color": "0",
    "project_hex_color": "#e36a00",
    "task": null,
    "billable": null,
    "is_billable": false,
    "cur": null,
    "tags": []
  },
  {
    "id": 2370897058,
    "pid": 176309420,
    "tid": null,
    "uid": 5298429,
    "description": "FoE",
    "start": "2022-02-15T17:30:34+01:00",
    "end": "2022-02-15T17:46:38+01:00",
    "updated": "2022-02-15T17:46:39+01:00",
    "dur": 964000,
    "user": "Huy",
    "use_stop": true,
    "client": "Fun",
    "project": "Gaming",
    "project_color": "0",
    "project_hex_color": "#2da608",
    "task": null,
    "billable": null,
    "is_billable": false,
    "cur": null,
    "tags": []
  },
  {
    "id": 2370735411,
    "pid": 176309103,
    "tid": null,
    "uid": 5298429,
    "description": "Sleep",
    "start": "2022-02-15T16:16:52+01:00",
    "end": "2022-02-15T17:30:32+01:00",
    "updated": "2022-02-15T17:30:33+01:00",
    "dur": 4420000,
    "user": "Huy",
    "use_stop": true,
    "client": "Sleep",
    "project": "Sleep",
    "project_color": "0",
    "project_hex_color": "#525266",
    "task": null,
    "billable": null,
    "is_billable": false,
    "cur": null,
    "tags": []
  },
  {
    "id": 2370343752,
    "pid": 158317561,
    "tid": null,
    "uid": 5298429,
    "description": "Scripting",
    "start": "2022-02-15T13:04:07+01:00",
    "end": "2022-02-15T16:16:52+01:00",
    "updated": "2022-02-15T16:16:54+01:00",
    "dur": 11565000,
    "user": "Huy",
    "use_stop": true,
    "client": "Fun & Future",
    "project": "Coding Projects",
    "project_color": "0",
    "project_hex_color": "#e36a00",
    "task": null,
    "billable": null,
    "is_billable": false,
    "cur": null,
    "tags": []
  },
  {
    "id": 2370121761,
    "pid": 177268557,
    "tid": null,
    "uid": 5298429,
    "description": "Relax",
    "start": "2022-02-15T10:48:08+01:00",
    "end": "2022-02-15T13:04:03+01:00",
    "updated": "2022-02-15T13:04:04+01:00",
    "dur": 8155000,
    "user": "Huy",
    "use_stop": true,
    "client": "Fun",
    "project": "Feel Comfortable",
    "project_color": "0",
    "project_hex_color": "#9e5bd9",
    "task": null,
    "billable": null,
    "is_billable": false,
    "cur": null,
    "tags": []
  },
  {
    "id": 2370120774,
    "pid": 176309103,
    "tid": null,
    "uid": 5298429,
    "description": "Sleep",
    "start": "2022-02-15T00:00:00+01:00",
    "end": "2022-02-15T10:48:06+01:00",
    "updated": "2022-02-15T10:48:08+01:00",
    "dur": 38886000,
    "user": "Huy",
    "use_stop": true,
    "client": "Sleep",
    "project": "Sleep",
    "project_color": "0",
    "project_hex_color": "#525266",
    "task": null,
    "billable": null,
    "is_billable": false,
    "cur": null,
    "tags": []
  },
  {
    "id": 2369326204,
    "pid": 176309651,
    "tid": null,
    "uid": 5298429,
    "description": "Laura",
    "start": "2022-02-14T21:25:47+01:00",
    "end": "2022-02-15T00:00:00+01:00",
    "updated": "2022-02-15T10:47:55+01:00",
    "dur": 9253000,
    "user": "Huy",
    "use_stop": true,
    "client": "Fun",
    "project": "Relationships",
    "project_color": "0",
    "project_hex_color": "#d94182",
    "task": null,
    "billable": null,
    "is_billable": false,
    "cur": null,
    "tags": []
  },
  {
    "id": 2368964706,
    "pid": 177268557,
    "tid": null,
    "uid": 5298429,
    "description": "Relax",
    "start": "2022-02-14T17:42:07+01:00",
    "end": "2022-02-14T21:25:46+01:00",
    "updated": "2022-02-14T21:25:47+01:00",
    "dur": 13419000,
    "user": "Huy",
    "use_stop": true,
    "client": "Fun",
    "project": "Feel Comfortable",
    "project_color": "0",
    "project_hex_color": "#9e5bd9",
    "task": null,
    "billable": null,
    "is_billable": false,
    "cur": null,
    "tags": []
  },
  {
    "id": 2368865168,
    "pid": 176309267,
    "tid": null,
    "uid": 5298429,
    "description": "Hygiene",
    "start": "2022-02-14T17:00:48+01:00",
    "end": "2022-02-14T17:42:06+01:00",
    "updated": "2022-02-14T17:42:06+01:00",
    "dur": 2478000,
    "user": "Huy",
    "use_stop": true,
    "client": "Future",
    "project": "Necessary",
    "project_color": "0",
    "project_hex_color": "#0b83d9",
    "task": null,
    "billable": null,
    "is_billable": false,
    "cur": null,
    "tags": []
  },
  {
    "id": 2368817810,
    "pid": 158317561,
    "tid": null,
    "uid": 5298429,
    "description": "Scripting",
    "start": "2022-02-14T15:45:00+01:00",
    "end": "2022-02-14T17:00:47+01:00",
    "updated": "2022-02-14T17:00:48+01:00",
    "dur": 4547000,
    "user": "Huy",
    "use_stop": true,
    "client": "Fun & Future",
    "project": "Coding Projects",
    "project_color": "0",
    "project_hex_color": "#e36a00",
    "task": null,
    "billable": null,
    "is_billable": false,
    "cur": null,
    "tags": []
  },
  {
    "id": 2368292503,
    "pid": 177268557,
    "tid": null,
    "uid": 5298429,
    "description": "Relax",
    "start": "2022-02-14T12:00:00+01:00",
    "end": "2022-02-14T15:45:00+01:00",
    "updated": "2022-02-14T16:39:04+01:00",
    "dur": 13500000,
    "user": "Huy",
    "use_stop": true,
    "client": "Fun",
    "project": "Feel Comfortable",
    "project_color": "0",
    "project_hex_color": "#9e5bd9",
    "task": null,
    "billable": null,
    "is_billable": false,
    "cur": null,
    "tags": []
  },
  {
    "id": 2367625436,
    "pid": 176309103,
    "tid": null,
    "uid": 5298429,
    "description": "Sleep",
    "start": "2022-02-14T01:27:08+01:00",
    "end": "2022-02-14T12:00:00+01:00",
    "updated": "2022-02-14T12:21:38+01:00",
    "dur": 37972000,
    "user": "Huy",
    "use_stop": true,
    "client": "Sleep",
    "project": "Sleep",
    "project_color": "0",
    "project_hex_color": "#525266",
    "task": null,
    "billable": null,
    "is_billable": false,
    "cur": null,
    "tags": []
  },
  {
    "id": 2367515989,
    "pid": 177268557,
    "tid": null,
    "uid": 5298429,
    "description": "Relax",
    "start": "2022-02-13T21:15:10+01:00",
    "end": "2022-02-14T01:27:07+01:00",
    "updated": "2022-02-14T01:27:09+01:00",
    "dur": 15117000,
    "user": "Huy",
    "use_stop": true,
    "client": "Fun",
    "project": "Feel Comfortable",
    "project_color": "0",
    "project_hex_color": "#9e5bd9",
    "task": null,
    "billable": null,
    "is_billable": false,
    "cur": null,
    "tags": []
  },
  {
    "id": 2367499378,
    "pid": 176309267,
    "tid": null,
    "uid": 5298429,
    "description": "Cooking & Eating",
    "start": "2022-02-13T20:38:43+01:00",
    "end": "2022-02-13T21:15:09+01:00",
    "updated": "2022-02-13T21:15:57+01:00",
    "dur": 2186000,
    "user": "Huy",
    "use_stop": true,
    "client": "Future",
    "project": "Necessary",
    "project_color": "0",
    "project_hex_color": "#0b83d9",
    "task": null,
    "billable": null,
    "is_billable": false,
    "cur": null,
    "tags": []
  },
  {
    "id": 2367499377,
    "pid": 177005400,
    "tid": null,
    "uid": 5298429,
    "description": "Bouldering",
    "start": "2022-02-13T18:45:00+01:00",
    "end": "2022-02-13T20:38:43+01:00",
    "updated": "2022-02-13T20:39:23+01:00",
    "dur": 6823000,
    "user": "Huy",
    "use_stop": true,
    "client": "Fun",
    "project": "Exercise",
    "project_color": "0",
    "project_hex_color": "#c7af14",
    "task": null,
    "billable": null,
    "is_billable": false,
    "cur": null,
    "tags": []
  },
  {
    "id": 2367290130,
    "pid": 177268557,
    "tid": null,
    "uid": 5298429,
    "description": "Relax",
    "start": "2022-02-13T10:07:07+01:00",
    "end": "2022-02-13T18:45:00+01:00",
    "updated": "2022-02-13T20:39:23+01:00",
    "dur": 31073000,
    "user": "Huy",
    "use_stop": true,
    "client": "Fun",
    "project": "Feel Comfortable",
    "project_color": "0",
    "project_hex_color": "#9e5bd9",
    "task": null,
    "billable": null,
    "is_billable": false,
    "cur": null,
    "tags": []
  },
  {
    "id": 2367290081,
    "pid": 176309103,
    "tid": null,
    "uid": 5298429,
    "description": "Sleep",
    "start": "2022-02-13T01:45:00+01:00",
    "end": "2022-02-13T10:07:06+01:00",
    "updated": "2022-02-13T10:07:14+01:00",
    "dur": 30126000,
    "user": "Huy",
    "use_stop": true,
    "client": "Sleep",
    "project": "Sleep",
    "project_color": "0",
    "project_hex_color": "#525266",
    "task": null,
    "billable": null,
    "is_billable": false,
    "cur": null,
    "tags": []
  },
  {
    "id": 2367038813,
    "pid": 177268557,
    "tid": null,
    "uid": 5298429,
    "description": "Relax",
    "start": "2022-02-12T16:07:53+01:00",
    "end": "2022-02-13T01:45:00+01:00",
    "updated": "2022-02-13T10:07:03+01:00",
    "dur": 34627000,
    "user": "Huy",
    "use_stop": true,
    "client": "Fun",
    "project": "Feel Comfortable",
    "project_color": "0",
    "project_hex_color": "#9e5bd9",
    "task": null,
    "billable": null,
    "is_billable": false,
    "cur": null,
    "tags": []
  },
  {
    "id": 2367031172,
    "pid": 176309267,
    "tid": null,
    "uid": 5298429,
    "description": "Cooking & Eating",
    "start": "2022-02-12T15:44:21+01:00",
    "end": "2022-02-12T16:07:51+01:00",
    "updated": "2022-02-12T16:07:53+01:00",
    "dur": 1410000,
    "user": "Huy",
    "use_stop": true,
    "client": "Future",
    "project": "Necessary",
    "project_color": "0",
    "project_hex_color": "#0b83d9",
    "task": null,
    "billable": null,
    "is_billable": false,
    "cur": null,
    "tags": []
  },
  {
    "id": 2367016342,
    "pid": 176309420,
    "tid": null,
    "uid": 5298429,
    "description": "Smash",
    "start": "2022-02-12T14:58:05+01:00",
    "end": "2022-02-12T15:44:11+01:00",
    "updated": "2022-02-12T15:44:13+01:00",
    "dur": 2766000,
    "user": "Huy",
    "use_stop": true,
    "client": "Fun",
    "project": "Gaming",
    "project_color": "0",
    "project_hex_color": "#2da608",
    "task": null,
    "billable": null,
    "is_billable": false,
    "cur": null,
    "tags": []
  },
  {
    "id": 2367011270,
    "pid": 158317561,
    "tid": null,
    "uid": 5298429,
    "description": "Spot_that_fi",
    "start": "2022-02-12T14:40:58+01:00",
    "end": "2022-02-12T14:56:27+01:00",
    "updated": "2022-02-12T14:56:28+01:00",
    "dur": 929000,
    "user": "Huy",
    "use_stop": true,
    "client": "Fun & Future",
    "project": "Coding Projects",
    "project_color": "0",
    "project_hex_color": "#e36a00",
    "task": null,
    "billable": null,
    "is_billable": false,
    "cur": null,
    "tags": []
  },
  {
    "id": 2367002539,
    "pid": 177268557,
    "tid": null,
    "uid": 5298429,
    "description": "Relax",
    "start": "2022-02-12T14:11:56+01:00",
    "end": "2022-02-12T14:40:58+01:00",
    "updated": "2022-02-12T14:40:59+01:00",
    "dur": 1742000,
    "user": "Huy",
    "use_stop": true,
    "client": "Fun",
    "project": "Feel Comfortable",
    "project_color": "0",
    "project_hex_color": "#9e5bd9",
    "task": null,
    "billable": null,
    "is_billable": false,
    "cur": null,
    "tags": []
  },
  {
    "id": 2366999928,
    "pid": 176309267,
    "tid": null,
    "uid": 5298429,
    "description": "Grocery shopping",
    "start": "2022-02-12T14:03:14+01:00",
    "end": "2022-02-12T14:11:56+01:00",
    "updated": "2022-02-12T14:11:58+01:00",
    "dur": 522000,
    "user": "Huy",
    "use_stop": true,
    "client": "Future",
    "project": "Necessary",
    "project_color": "0",
    "project_hex_color": "#0b83d9",
    "task": null,
    "billable": null,
    "is_billable": false,
    "cur": null,
    "tags": []
  },
  {
    "id": 2366993259,
    "pid": 176309267,
    "tid": null,
    "uid": 5298429,
    "description": "Cooking & Eating",
    "start": "2022-02-12T13:40:09+01:00",
    "end": "2022-02-12T14:03:00+01:00",
    "updated": "2022-02-12T14:03:01+01:00",
    "dur": 1371000,
    "user": "Huy",
    "use_stop": true,
    "client": "Future",
    "project": "Necessary",
    "project_color": "0",
    "project_hex_color": "#0b83d9",
    "task": null,
    "billable": null,
    "is_billable": false,
    "cur": null,
    "tags": []
  },
  {
    "id": 2366992236,
    "pid": 158317561,
    "tid": null,
    "uid": 5298429,
    "description": "Spot_that_fi",
    "start": "2022-02-12T13:36:15+01:00",
    "end": "2022-02-12T13:40:09+01:00",
    "updated": "2022-02-12T13:40:11+01:00",
    "dur": 234000,
    "user": "Huy",
    "use_stop": true,
    "client": "Fun & Future",
    "project": "Coding Projects",
    "project_color": "0",
    "project_hex_color": "#e36a00",
    "task": null,
    "billable": null,
    "is_billable": false,
    "cur": null,
    "tags": []
  },
  {
    "id": 2366940071,
    "pid": 177268557,
    "tid": null,
    "uid": 5298429,
    "description": "Relax",
    "start": "2022-02-12T10:18:18+01:00",
    "end": "2022-02-12T13:36:01+01:00",
    "updated": "2022-02-12T13:36:03+01:00",
    "dur": 11863000,
    "user": "Huy",
    "use_stop": true,
    "client": "Fun",
    "project": "Feel Comfortable",
    "project_color": "0",
    "project_hex_color": "#9e5bd9",
    "task": null,
    "billable": null,
    "is_billable": false,
    "cur": null,
    "tags": []
  },
  {
    "id": 2366939937,
    "pid": 176309103,
    "tid": null,
    "uid": 5298429,
    "description": "Sleep",
    "start": "2022-02-12T02:15:00+01:00",
    "end": "2022-02-12T10:18:17+01:00",
    "updated": "2022-02-12T10:18:20+01:00",
    "dur": 28997000,
    "user": "Huy",
    "use_stop": true,
    "client": "Sleep",
    "project": "Sleep",
    "project_color": "0",
    "project_hex_color": "#525266",
    "task": null,
    "billable": null,
    "is_billable": false,
    "cur": null,
    "tags": []
  },
  {
    "id": 2366369884,
    "pid": 177268557,
    "tid": null,
    "uid": 5298429,
    "description": "Relax",
    "start": "2022-02-11T16:45:00+01:00",
    "end": "2022-02-12T02:15:00+01:00",
    "updated": "2022-02-12T10:18:07+01:00",
    "dur": 34200000,
    "user": "Huy",
    "use_stop": true,
    "client": "Fun",
    "project": "Feel Comfortable",
    "project_color": "0",
    "project_hex_color": "#9e5bd9",
    "task": null,
    "billable": null,
    "is_billable": false,
    "cur": null,
    "tags": []
  },
  {
    "id": 2366153647,
    "pid": 176309267,
    "tid": null,
    "uid": 5298429,
    "description": "Cooking & Eating",
    "start": "2022-02-11T15:30:00+01:00",
    "end": "2022-02-11T16:45:00+01:00",
    "updated": "2022-02-11T17:59:09+01:00",
    "dur": 4500000,
    "user": "Huy",
    "use_stop": true,
    "client": "Future",
    "project": "Necessary",
    "project_color": "0",
    "project_hex_color": "#0b83d9",
    "task": null,
    "billable": null,
    "is_billable": false,
    "cur": null,
    "tags": []
  },
  {
    "id": 2366029975,
    "pid": 177268557,
    "tid": null,
    "uid": 5298429,
    "description": "Relax",
    "start": "2022-02-11T15:12:14+01:00",
    "end": "2022-02-11T15:30:00+01:00",
    "updated": "2022-02-11T15:57:00+01:00",
    "dur": 1066000,
    "user": "Huy",
    "use_stop": true,
    "client": "Fun",
    "project": "Feel Comfortable",
    "project_color": "0",
    "project_hex_color": "#9e5bd9",
    "task": null,
    "billable": null,
    "is_billable": false,
    "cur": null,
    "tags": []
  },
  {
    "id": 2365957919,
    "pid": 176309267,
    "tid": null,
    "uid": 5298429,
    "description": "Organizing",
    "start": "2022-02-11T14:32:12+01:00",
    "end": "2022-02-11T15:12:14+01:00",
    "updated": "2022-02-11T15:12:15+01:00",
    "dur": 2402000,
    "user": "Huy",
    "use_stop": true,
    "client": "Future",
    "project": "Necessary",
    "project_color": "0",
    "project_hex_color": "#0b83d9",
    "task": null,
    "billable": null,
    "is_billable": false,
    "cur": null,
    "tags": []
  },
  {
    "id": 2365821474,
    "pid": 177268557,
    "tid": null,
    "uid": 5298429,
    "description": "Relax",
    "start": "2022-02-11T13:04:51+01:00",
    "end": "2022-02-11T14:32:12+01:00",
    "updated": "2022-02-11T14:32:14+01:00",
    "dur": 5241000,
    "user": "Huy",
    "use_stop": true,
    "client": "Fun",
    "project": "Feel Comfortable",
    "project_color": "0",
    "project_hex_color": "#9e5bd9",
    "task": null,
    "billable": null,
    "is_billable": false,
    "cur": null,
    "tags": []
  },
  {
    "id": 2365801911,
    "pid": 176309267,
    "tid": null,
    "uid": 5298429,
    "description": "Hygiene",
    "start": "2022-02-11T12:51:45+01:00",
    "end": "2022-02-11T13:04:51+01:00",
    "updated": "2022-02-11T13:04:53+01:00",
    "dur": 786000,
    "user": "Huy",
    "use_stop": true,
    "client": "Future",
    "project": "Necessary",
    "project_color": "0",
    "project_hex_color": "#0b83d9",
    "task": null,
    "billable": null,
    "is_billable": false,
    "cur": null,
    "tags": []
  },
  {
    "id": 2365790391,
    "pid": 176309267,
    "tid": null,
    "uid": 5298429,
    "description": "Cooking & Eating",
    "start": "2022-02-11T12:43:19+01:00",
    "end": "2022-02-11T12:51:39+01:00",
    "updated": "2022-02-11T12:51:44+01:00",
    "dur": 500000,
    "user": "Huy",
    "use_stop": true,
    "client": "Future",
    "project": "Necessary",
    "project_color": "0",
    "project_hex_color": "#0b83d9",
    "task": null,
    "billable": null,
    "is_billable": false,
    "cur": null,
    "tags": []
  },
  {
    "id": 2365703146,
    "pid": 177268557,
    "tid": null,
    "uid": 5298429,
    "description": "Relax",
    "start": "2022-02-11T11:38:20+01:00",
    "end": "2022-02-11T12:43:19+01:00",
    "updated": "2022-02-11T12:43:24+01:00",
    "dur": 3899000,
    "user": "Huy",
    "use_stop": true,
    "client": "Fun",
    "project": "Feel Comfortable",
    "project_color": "0",
    "project_hex_color": "#9e5bd9",
    "task": null,
    "billable": null,
    "is_billable": false,
    "cur": null,
    "tags": []
  },
  {
    "id": 2365571044,
    "pid": 176309267,
    "tid": null,
    "uid": 5298429,
    "description": "Morning Routine",
    "start": "2022-02-11T10:07:35+01:00",
    "end": "2022-02-11T11:38:20+01:00",
    "updated": "2022-02-11T11:38:21+01:00",
    "dur": 5445000,
    "user": "Huy",
    "use_stop": true,
    "client": "Future",
    "project": "Necessary",
    "project_color": "0",
    "project_hex_color": "#0b83d9",
    "task": null,
    "billable": null,
    "is_billable": false,
    "cur": null,
    "tags": []
  },
  {
    "id": 2365193350,
    "pid": 176309103,
    "tid": null,
    "uid": 5298429,
    "description": "Sleep",
    "start": "2022-02-11T02:07:56+01:00",
    "end": "2022-02-11T10:07:34+01:00",
    "updated": "2022-02-11T10:07:36+01:00",
    "dur": 28778000,
    "user": "Huy",
    "use_stop": true,
    "client": "Sleep",
    "project": "Sleep",
    "project_color": "0",
    "project_hex_color": "#525266",
    "task": null,
    "billable": null,
    "is_billable": false,
    "cur": null,
    "tags": []
  },
  {
    "id": 2364957670,
    "pid": 177268557,
    "tid": null,
    "uid": 5298429,
    "description": "Relax",
    "start": "2022-02-10T22:04:47+01:00",
    "end": "2022-02-11T02:07:56+01:00",
    "updated": "2022-02-11T02:07:58+01:00",
    "dur": 14589000,
    "user": "Huy",
    "use_stop": true,
    "client": "Fun",
    "project": "Feel Comfortable",
    "project_color": "0",
    "project_hex_color": "#9e5bd9",
    "task": null,
    "billable": null,
    "is_billable": false,
    "cur": null,
    "tags": []
  },
  {
    "id": 2364905214,
    "pid": 176309267,
    "tid": null,
    "uid": 5298429,
    "description": "Cooking & Eating",
    "start": "2022-02-10T21:26:10+01:00",
    "end": "2022-02-10T22:04:47+01:00",
    "updated": "2022-02-10T22:04:49+01:00",
    "dur": 2317000,
    "user": "Huy",
    "use_stop": true,
    "client": "Future",
    "project": "Necessary",
    "project_color": "0",
    "project_hex_color": "#0b83d9",
    "task": null,
    "billable": null,
    "is_billable": false,
    "cur": null,
    "tags": []
  },
  {
    "id": 2363953474,
    "pid": 177268557,
    "tid": null,
    "uid": 5298429,
    "description": "Relax",
    "start": "2022-02-10T12:24:19+01:00",
    "end": "2022-02-10T21:26:09+01:00",
    "updated": "2022-02-10T21:26:10+01:00",
    "dur": 32510000,
    "user": "Huy",
    "use_stop": true,
    "client": "Fun",
    "project": "Feel Comfortable",
    "project_color": "0",
    "project_hex_color": "#9e5bd9",
    "task": null,
    "billable": null,
    "is_billable": false,
    "cur": null,
    "tags": []
  },
  {
    "id": 2363900281,
    "pid": 176309651,
    "tid": null,
    "uid": 5298429,
    "description": "Laura",
    "start": "2022-02-10T11:15:00+01:00",
    "end": "2022-02-10T12:24:18+01:00",
    "updated": "2022-02-10T12:24:20+01:00",
    "dur": 4158000,
    "user": "Huy",
    "use_stop": true,
    "client": "Fun",
    "project": "Relationships",
    "project_color": "0",
    "project_hex_color": "#d94182",
    "task": null,
    "billable": null,
    "is_billable": false,
    "cur": null,
    "tags": []
  },
  {
    "id": 2363899671,
    "pid": 176309103,
    "tid": null,
    "uid": 5298429,
    "description": "Sleep",
    "start": "2022-02-10T02:00:00+01:00",
    "end": "2022-02-10T11:15:00+01:00",
    "updated": "2022-02-10T11:49:44+01:00",
    "dur": 33300000,
    "user": "Huy",
    "use_stop": true,
    "client": "Sleep",
    "project": "Sleep",
    "project_color": "0",
    "project_hex_color": "#525266",
    "task": null,
    "billable": null,
    "is_billable": false,
    "cur": null,
    "tags": []
  },
  {
    "id": 2362719885,
    "pid": 176309651,
    "tid": null,
    "uid": 5298429,
    "description": "Laura",
    "start": "2022-02-09T18:09:23+01:00",
    "end": "2022-02-10T02:00:00+01:00",
    "updated": "2022-02-10T11:49:27+01:00",
    "dur": 28237000,
    "user": "Huy",
    "use_stop": true,
    "client": "Fun",
    "project": "Relationships",
    "project_color": "0",
    "project_hex_color": "#d94182",
    "task": null,
    "billable": null,
    "is_billable": false,
    "cur": null,
    "tags": []
  },
  {
    "id": 2362564358,
    "pid": 158317561,
    "tid": null,
    "uid": 5298429,
    "description": "Scripting",
    "start": "2022-02-09T16:52:50+01:00",
    "end": "2022-02-09T18:09:20+01:00",
    "updated": "2022-02-09T18:09:24+01:00",
    "dur": 4590000,
    "user": "Huy",
    "use_stop": true,
    "client": "Fun & Future",
    "project": "Coding Projects",
    "project_color": "0",
    "project_hex_color": "#e36a00",
    "task": null,
    "billable": null,
    "is_billable": false,
    "cur": null,
    "tags": []
  },
  {
    "id": 2362128283,
    "pid": 177268557,
    "tid": null,
    "uid": 5298429,
    "description": "Relax",
    "start": "2022-02-09T13:14:28+01:00",
    "end": "2022-02-09T16:52:49+01:00",
    "updated": "2022-02-09T16:52:51+01:00",
    "dur": 13101000,
    "user": "Huy",
    "use_stop": true,
    "client": "Fun",
    "project": "Feel Comfortable",
    "project_color": "0",
    "project_hex_color": "#9e5bd9",
    "task": null,
    "billable": null,
    "is_billable": false,
    "cur": null,
    "tags": []
  },
  {
    "id": 2362030384,
    "pid": 176309267,
    "tid": null,
    "uid": 5298429,
    "description": "Morning Routine",
    "start": "2022-02-09T12:07:35+01:00",
    "end": "2022-02-09T13:14:28+01:00",
    "updated": "2022-02-09T13:14:30+01:00",
    "dur": 4013000,
    "user": "Huy",
    "use_stop": true,
    "client": "Future",
    "project": "Necessary",
    "project_color": "0",
    "project_hex_color": "#0b83d9",
    "task": null,
    "billable": null,
    "is_billable": false,
    "cur": null,
    "tags": []
  },
  {
    "id": 2362022705,
    "pid": 176309103,
    "tid": null,
    "uid": 5298429,
    "description": "Sleep",
    "start": "2022-02-09T07:00:00+01:00",
    "end": "2022-02-09T16:52:34+01:00",
    "updated": "2022-02-09T12:12:25+01:00",
    "dur": 35554000,
    "user": "Huy",
    "use_stop": true,
    "client": "Sleep",
    "project": "Sleep",
    "project_color": "0",
    "project_hex_color": "#525266",
    "task": null,
    "billable": null,
    "is_billable": false,
    "cur": null,
    "tags": []
  },
  {
    "id": 2360769821,
    "pid": 177268557,
    "tid": null,
    "uid": 5298429,
    "description": "Relax",
    "start": "2022-02-08T17:57:23+01:00",
    "end": "2022-02-09T02:15:00+01:00",
    "updated": "2022-02-09T12:07:27+01:00",
    "dur": 29857000,
    "user": "Huy",
    "use_stop": true,
    "client": "Fun",
    "project": "Feel Comfortable",
    "project_color": "0",
    "project_hex_color": "#9e5bd9",
    "task": null,
    "billable": null,
    "is_billable": false,
    "cur": null,
    "tags": []
  },
  {
    "id": 2360769443,
    "pid": 177005400,
    "tid": null,
    "uid": 5298429,
    "description": "Bouldering",
    "start": "2022-02-08T16:00:00+01:00",
    "end": "2022-02-08T17:57:22+01:00",
    "updated": "2022-02-08T17:57:30+01:00",
    "dur": 7042000,
    "user": "Huy",
    "use_stop": true,
    "client": "Fun",
    "project": "Exercise",
    "project_color": "0",
    "project_hex_color": "#c7af14",
    "task": null,
    "billable": null,
    "is_billable": false,
    "cur": null,
    "tags": []
  },
  {
    "id": 2360338314,
    "pid": 177268557,
    "tid": null,
    "uid": 5298429,
    "description": "Relax",
    "start": "2022-02-08T14:41:14+01:00",
    "end": "2022-02-08T16:00:00+01:00",
    "updated": "2022-02-08T17:57:18+01:00",
    "dur": 4726000,
    "user": "Huy",
    "use_stop": true,
    "client": "Fun",
    "project": "Feel Comfortable",
    "project_color": "0",
    "project_hex_color": "#9e5bd9",
    "task": null,
    "billable": null,
    "is_billable": false,
    "cur": null,
    "tags": []
  },
  {
    "id": 2360249604,
    "pid": 176309267,
    "tid": null,
    "uid": 5298429,
    "description": "Cooking & Eating",
    "start": "2022-02-08T14:07:39+01:00",
    "end": "2022-02-08T14:41:14+01:00",
    "updated": "2022-02-08T14:41:15+01:00",
    "dur": 2015000,
    "user": "Huy",
    "use_stop": true,
    "client": "Future",
    "project": "Necessary",
    "project_color": "0",
    "project_hex_color": "#0b83d9",
    "task": null,
    "billable": null,
    "is_billable": false,
    "cur": null,
    "tags": []
  },
  {
    "id": 2359872003,
    "pid": 177268557,
    "tid": null,
    "uid": 5298429,
    "description": "Relax",
    "start": "2022-02-08T10:26:39+01:00",
    "end": "2022-02-08T14:07:39+01:00",
    "updated": "2022-02-08T14:07:40+01:00",
    "dur": 13260000,
    "user": "Huy",
    "use_stop": true,
    "client": "Fun",
    "project": "Feel Comfortable",
    "project_color": "0",
    "project_hex_color": "#9e5bd9",
    "task": null,
    "billable": null,
    "is_billable": false,
    "cur": null,
    "tags": []
  },
  {
    "id": 2359871084,
    "pid": 176309103,
    "tid": null,
    "uid": 5298429,
    "description": "Sleep",
    "start": "2022-02-08T01:45:00+01:00",
    "end": "2022-02-08T10:26:38+01:00",
    "updated": "2022-02-08T13:52:17+01:00",
    "dur": 31298000,
    "user": "Huy",
    "use_stop": true,
    "client": "Sleep",
    "project": "Sleep",
    "project_color": "0",
    "project_hex_color": "#525266",
    "task": null,
    "billable": null,
    "is_billable": false,
    "cur": null,
    "tags": []
  },
  {
    "id": 2358963240,
    "pid": 177268557,
    "tid": null,
    "uid": 5298429,
    "description": "Relax",
    "start": "2022-02-07T18:15:00+01:00",
    "end": "2022-02-08T01:45:00+01:00",
    "updated": "2022-02-08T10:26:20+01:00",
    "dur": 27000000,
    "user": "Huy",
    "use_stop": true,
    "client": "Fun",
    "project": "Feel Comfortable",
    "project_color": "0",
    "project_hex_color": "#9e5bd9",
    "task": null,
    "billable": null,
    "is_billable": false,
    "cur": null,
    "tags": []
  },
  {
    "id": 2358459820,
    "pid": 158317561,
    "tid": null,
    "uid": 5298429,
    "description": "Scripting",
    "start": "2022-02-07T15:53:56+01:00",
    "end": "2022-02-07T18:15:00+01:00",
    "updated": "2022-02-07T20:04:01+01:00",
    "dur": 8464000,
    "user": "Huy",
    "use_stop": true,
    "client": "Fun & Future",
    "project": "Coding Projects",
    "project_color": "0",
    "project_hex_color": "#e36a00",
    "task": null,
    "billable": null,
    "is_billable": false,
    "cur": null,
    "tags": []
  },
  {
    "id": 2358362481,
    "pid": 177268557,
    "tid": null,
    "uid": 5298429,
    "description": "Relax",
    "start": "2022-02-07T14:32:54+01:00",
    "end": "2022-02-07T15:53:56+01:00",
    "updated": "2022-02-07T15:53:59+01:00",
    "dur": 4862000,
    "user": "Huy",
    "use_stop": true,
    "client": "Fun",
    "project": "Feel Comfortable",
    "project_color": "0",
    "project_hex_color": "#9e5bd9",
    "task": null,
    "billable": null,
    "is_billable": false,
    "cur": null,
    "tags": []
  },
  {
    "id": 2358268353,
    "pid": 176309267,
    "tid": null,
    "uid": 5298429,
    "description": "Organizing",
    "start": "2022-02-07T13:30:00+01:00",
    "end": "2022-02-07T14:32:54+01:00",
    "updated": "2022-02-07T15:11:45+01:00",
    "dur": 3774000,
    "user": "Huy",
    "use_stop": true,
    "client": "Future",
    "project": "Necessary",
    "project_color": "0",
    "project_hex_color": "#0b83d9",
    "task": null,
    "billable": null,
    "is_billable": false,
    "cur": null,
    "tags": []
  },
  {
    "id": 2357845030,
    "pid": 177268557,
    "tid": null,
    "uid": 5298429,
    "description": "Relax",
    "start": "2022-02-07T10:33:54+01:00",
    "end": "2022-02-07T13:30:00+01:00",
    "updated": "2022-02-07T14:29:12+01:00",
    "dur": 10566000,
    "user": "Huy",
    "use_stop": true,
    "client": "Fun",
    "project": "Feel Comfortable",
    "project_color": "0",
    "project_hex_color": "#9e5bd9",
    "task": null,
    "billable": null,
    "is_billable": false,
    "cur": null,
    "tags": []
  },
  {
    "id": 2357324432,
    "pid": 176309103,
    "tid": null,
    "uid": 5298429,
    "description": "Sleep",
    "start": "2022-02-07T00:32:17+01:00",
    "end": "2022-02-07T10:33:53+01:00",
    "updated": "2022-02-07T10:33:55+01:00",
    "dur": 36096000,
    "user": "Huy",
    "use_stop": true,
    "client": "Sleep",
    "project": "Sleep",
    "project_color": "0",
    "project_hex_color": "#525266",
    "task": null,
    "billable": null,
    "is_billable": false,
    "cur": null,
    "tags": []
  },
  {
    "id": 2357215029,
    "pid": 176309651,
    "tid": null,
    "uid": 5298429,
    "description": "Friends",
    "start": "2022-02-06T22:32:51+01:00",
    "end": "2022-02-07T00:32:16+01:00",
    "updated": "2022-02-07T00:32:18+01:00",
    "dur": 7165000,
    "user": "Huy",
    "use_stop": true,
    "client": "Fun",
    "project": "Relationships",
    "project_color": "0",
    "project_hex_color": "#d94182",
    "task": null,
    "billable": null,
    "is_billable": false,
    "cur": null,
    "tags": []
  },
  {
    "id": 2357161937,
    "pid": 177005400,
    "tid": null,
    "uid": 5298429,
    "description": "Bouldering",
    "start": "2022-02-06T20:19:22+01:00",
    "end": "2022-02-06T22:32:50+01:00",
    "updated": "2022-02-06T22:32:53+01:00",
    "dur": 8008000,
    "user": "Huy",
    "use_stop": true,
    "client": "Fun",
    "project": "Exercise",
    "project_color": "0",
    "project_hex_color": "#c7af14",
    "task": null,
    "billable": null,
    "is_billable": false,
    "cur": null,
    "tags": []
  },
  {
    "id": 2357036355,
    "pid": 177268557,
    "tid": null,
    "uid": 5298429,
    "description": "Relax",
    "start": "2022-02-06T13:55:10+01:00",
    "end": "2022-02-06T20:19:21+01:00",
    "updated": "2022-02-06T20:19:24+01:00",
    "dur": 23051000,
    "user": "Huy",
    "use_stop": true,
    "client": "Fun",
    "project": "Feel Comfortable",
    "project_color": "0",
    "project_hex_color": "#9e5bd9",
    "task": null,
    "billable": null,
    "is_billable": false,
    "cur": null,
    "tags": []
  },
  {
    "id": 2356983292,
    "pid": 176309267,
    "tid": null,
    "uid": 5298429,
    "description": "Organizing",
    "start": "2022-02-06T11:51:25+01:00",
    "end": "2022-02-06T13:55:10+01:00",
    "updated": "2022-02-06T14:42:29+01:00",
    "dur": 7425000,
    "user": "Huy",
    "use_stop": true,
    "client": "Future",
    "project": "Necessary",
    "project_color": "0",
    "project_hex_color": "#0b83d9",
    "task": null,
    "billable": null,
    "is_billable": false,
    "cur": null,
    "tags": []
  },
  {
    "id": 2356954157,
    "pid": 176309267,
    "tid": null,
    "uid": 5298429,
    "description": "Morning Routine",
    "start": "2022-02-06T10:07:45+01:00",
    "end": "2022-02-06T11:51:24+01:00",
    "updated": "2022-02-06T11:52:33+01:00",
    "dur": 6219000,
    "user": "Huy",
    "use_stop": true,
    "client": "Future",
    "project": "Necessary",
    "project_color": "0",
    "project_hex_color": "#0b83d9",
    "task": null,
    "billable": null,
    "is_billable": false,
    "cur": null,
    "tags": []
  },
  {
    "id": 2356855125,
    "pid": 176309103,
    "tid": null,
    "uid": 5298429,
    "description": "Sleep",
    "start": "2022-02-06T01:17:02+01:00",
    "end": "2022-02-06T10:07:45+01:00",
    "updated": "2022-02-06T10:07:48+01:00",
    "dur": 31843000,
    "user": "Huy",
    "use_stop": true,
    "client": "Sleep",
    "project": "Sleep",
    "project_color": "0",
    "project_hex_color": "#525266",
    "task": null,
    "billable": null,
    "is_billable": false,
    "cur": null,
    "tags": []
  },
  {
    "id": 2356814179,
    "pid": 177268557,
    "tid": null,
    "uid": 5298429,
    "description": "Relax",
    "start": "2022-02-05T19:00:00+01:00",
    "end": "2022-02-06T01:17:02+01:00",
    "updated": "2022-02-06T01:17:08+01:00",
    "dur": 22622000,
    "user": "Huy",
    "use_stop": true,
    "client": "Fun",
    "project": "Feel Comfortable",
    "project_color": "0",
    "project_hex_color": "#9e5bd9",
    "task": null,
    "billable": null,
    "is_billable": false,
    "cur": null,
    "tags": []
  },
  {
    "id": 2356745069,
    "pid": 162872800,
    "tid": null,
    "uid": 5298429,
    "description": "DJing",
    "start": "2022-02-05T17:30:00+01:00",
    "end": "2022-02-05T19:00:00+01:00",
    "updated": "2022-02-05T22:18:31+01:00",
    "dur": 5400000,
    "user": "Huy",
    "use_stop": true,
    "client": "Fun",
    "project": "Music",
    "project_color": "0",
    "project_hex_color": "#566614",
    "task": null,
    "billable": null,
    "is_billable": false,
    "cur": null,
    "tags": []
  },
  {
    "id": 2356641467,
    "pid": 177268557,
    "tid": null,
    "uid": 5298429,
    "description": "Relax",
    "start": "2022-02-05T12:58:54+01:00",
    "end": "2022-02-05T17:30:00+01:00",
    "updated": "2022-02-05T19:47:08+01:00",
    "dur": 16266000,
    "user": "Huy",
    "use_stop": true,
    "client": "Fun",
    "project": "Feel Comfortable",
    "project_color": "0",
    "project_hex_color": "#9e5bd9",
    "task": null,
    "billable": null,
    "is_billable": false,
    "cur": null,
    "tags": []
  },
  {
    "id": 2356629192,
    "pid": 176309267,
    "tid": null,
    "uid": 5298429,
    "description": "Cooking & Eating",
    "start": "2022-02-05T12:13:21+01:00",
    "end": "2022-02-05T12:58:54+01:00",
    "updated": "2022-02-05T12:58:56+01:00",
    "dur": 2733000,
    "user": "Huy",
    "use_stop": true,
    "client": "Future",
    "project": "Necessary",
    "project_color": "0",
    "project_hex_color": "#0b83d9",
    "task": null,
    "billable": null,
    "is_billable": false,
    "cur": null,
    "tags": []
  },
  {
    "id": 2356617335,
    "pid": 176309267,
    "tid": null,
    "uid": 5298429,
    "description": "Organizing",
    "start": "2022-02-05T11:28:59+01:00",
    "end": "2022-02-05T12:13:21+01:00",
    "updated": "2022-02-05T12:13:23+01:00",
    "dur": 2662000,
    "user": "Huy",
    "use_stop": true,
    "client": "Future",
    "project": "Necessary",
    "project_color": "0",
    "project_hex_color": "#0b83d9",
    "task": null,
    "billable": null,
    "is_billable": false,
    "cur": null,
    "tags": []
  },
  {
    "id": 2356605003,
    "pid": 177268557,
    "tid": null,
    "uid": 5298429,
    "description": "Relax",
    "start": "2022-02-05T10:41:36+01:00",
    "end": "2022-02-05T11:28:58+01:00",
    "updated": "2022-02-05T11:29:00+01:00",
    "dur": 2842000,
    "user": "Huy",
    "use_stop": true,
    "client": "Fun",
    "project": "Feel Comfortable",
    "project_color": "0",
    "project_hex_color": "#9e5bd9",
    "task": null,
    "billable": null,
    "is_billable": false,
    "cur": null,
    "tags": []
  },
  {
    "id": 2356604906,
    "pid": 176309103,
    "tid": null,
    "uid": 5298429,
    "description": "Sleep",
    "start": "2022-02-05T02:30:00+01:00",
    "end": "2022-02-05T10:41:34+01:00",
    "updated": "2022-02-05T10:41:40+01:00",
    "dur": 29494000,
    "user": "Huy",
    "use_stop": true,
    "client": "Sleep",
    "project": "Sleep",
    "project_color": "0",
    "project_hex_color": "#525266",
    "task": null,
    "billable": null,
    "is_billable": false,
    "cur": null,
    "tags": []
  },
  {
    "id": 2356019084,
    "pid": 177268557,
    "tid": null,
    "uid": 5298429,
    "description": "Relax",
    "start": "2022-02-04T18:01:09+01:00",
    "end": "2022-02-05T02:30:00+01:00",
    "updated": "2022-02-05T10:41:23+01:00",
    "dur": 30531000,
    "user": "Huy",
    "use_stop": true,
    "client": "Fun",
    "project": "Feel Comfortable",
    "project_color": "0",
    "project_hex_color": "#9e5bd9",
    "task": null,
    "billable": null,
    "is_billable": false,
    "cur": null,
    "tags": []
  },
  {
    "id": 2355853095,
    "pid": 176309267,
    "tid": null,
    "uid": 5298429,
    "description": "Cooking & Eating",
    "start": "2022-02-04T16:26:46+01:00",
    "end": "2022-02-04T18:01:09+01:00",
    "updated": "2022-02-04T18:01:11+01:00",
    "dur": 5663000,
    "user": "Huy",
    "use_stop": true,
    "client": "Future",
    "project": "Necessary",
    "project_color": "0",
    "project_hex_color": "#0b83d9",
    "task": null,
    "billable": null,
    "is_billable": false,
    "cur": null,
    "tags": []
  },
  {
    "id": 2355647973,
    "pid": 177268557,
    "tid": null,
    "uid": 5298429,
    "description": "Relax",
    "start": "2022-02-04T14:37:27+01:00",
    "end": "2022-02-04T16:26:46+01:00",
    "updated": "2022-02-04T16:26:51+01:00",
    "dur": 6559000,
    "user": "Huy",
    "use_stop": true,
    "client": "Fun",
    "project": "Feel Comfortable",
    "project_color": "0",
    "project_hex_color": "#9e5bd9",
    "task": null,
    "billable": null,
    "is_billable": false,
    "cur": null,
    "tags": []
  },
  {
    "id": 2355646622,
    "pid": 176309267,
    "tid": null,
    "uid": 5298429,
    "description": "Organizing",
    "start": "2022-02-04T13:30:00+01:00",
    "end": "2022-02-04T14:37:26+01:00",
    "updated": "2022-02-04T14:37:31+01:00",
    "dur": 4046000,
    "user": "Huy",
    "use_stop": true,
    "client": "Future",
    "project": "Necessary",
    "project_color": "0",
    "project_hex_color": "#0b83d9",
    "task": null,
    "billable": null,
    "is_billable": false,
    "cur": null,
    "tags": []
  },
  {
    "id": 2355403755,
    "pid": 177268557,
    "tid": null,
    "uid": 5298429,
    "description": "Relax",
    "start": "2022-02-04T11:54:31+01:00",
    "end": "2022-02-04T13:30:00+01:00",
    "updated": "2022-02-04T14:36:51+01:00",
    "dur": 5729000,
    "user": "Huy",
    "use_stop": true,
    "client": "Fun",
    "project": "Feel Comfortable",
    "project_color": "0",
    "project_hex_color": "#9e5bd9",
    "task": null,
    "billable": null,
    "is_billable": false,
    "cur": null,
    "tags": []
  },
  {
    "id": 2355375340,
    "pid": 176309267,
    "tid": null,
    "uid": 5298429,
    "description": "Cooking & Eating",
    "start": "2022-02-04T11:34:16+01:00",
    "end": "2022-02-04T11:54:31+01:00",
    "updated": "2022-02-04T11:54:36+01:00",
    "dur": 1215000,
    "user": "Huy",
    "use_stop": true,
    "client": "Future",
    "project": "Necessary",
    "project_color": "0",
    "project_hex_color": "#0b83d9",
    "task": null,
    "billable": null,
    "is_billable": false,
    "cur": null,
    "tags": []
  },
  {
    "id": 2355254923,
    "pid": 177268557,
    "tid": null,
    "uid": 5298429,
    "description": "Relax",
    "start": "2022-02-04T10:15:06+01:00",
    "end": "2022-02-04T11:34:16+01:00",
    "updated": "2022-02-04T11:34:19+01:00",
    "dur": 4750000,
    "user": "Huy",
    "use_stop": true,
    "client": "Fun",
    "project": "Feel Comfortable",
    "project_color": "0",
    "project_hex_color": "#9e5bd9",
    "task": null,
    "billable": null,
    "is_billable": false,
    "cur": null,
    "tags": []
  },
  {
    "id": 2355253784,
    "pid": 176309103,
    "tid": null,
    "uid": 5298429,
    "description": "Sleep",
    "start": "2022-02-04T01:30:00+01:00",
    "end": "2022-02-04T10:15:05+01:00",
    "updated": "2022-02-04T10:15:08+01:00",
    "dur": 31505000,
    "user": "Huy",
    "use_stop": true,
    "client": "Sleep",
    "project": "Sleep",
    "project_color": "0",
    "project_hex_color": "#525266",
    "task": null,
    "billable": null,
    "is_billable": false,
    "cur": null,
    "tags": []
  },
  {
    "id": 2354688094,
    "pid": 177268557,
    "tid": null,
    "uid": 5298429,
    "description": "Relax",
    "start": "2022-02-03T22:54:06+01:00",
    "end": "2022-02-04T01:30:00+01:00",
    "updated": "2022-02-04T10:14:43+01:00",
    "dur": 9354000,
    "user": "Huy",
    "use_stop": true,
    "client": "Fun",
    "project": "Feel Comfortable",
    "project_color": "0",
    "project_hex_color": "#9e5bd9",
    "task": null,
    "billable": null,
    "is_billable": false,
    "cur": null,
    "tags": []
  },
  {
    "id": 2354660198,
    "pid": 176309267,
    "tid": null,
    "uid": 5298429,
    "description": "Cooking & Eating",
    "start": "2022-02-03T22:00:00+01:00",
    "end": "2022-02-03T22:54:06+01:00",
    "updated": "2022-02-03T22:54:08+01:00",
    "dur": 3246000,
    "user": "Huy",
    "use_stop": true,
    "client": "Future",
    "project": "Necessary",
    "project_color": "0",
    "project_hex_color": "#0b83d9",
    "task": null,
    "billable": null,
    "is_billable": false,
    "cur": null,
    "tags": []
  },
  {
    "id": 2354221094,
    "pid": 177268557,
    "tid": null,
    "uid": 5298429,
    "description": "Relax",
    "start": "2022-02-03T17:35:07+01:00",
    "end": "2022-02-03T22:00:00+01:00",
    "updated": "2022-02-03T22:30:13+01:00",
    "dur": 15893000,
    "user": "Huy",
    "use_stop": true,
    "client": "Fun",
    "project": "Feel Comfortable",
    "project_color": "0",
    "project_hex_color": "#9e5bd9",
    "task": null,
    "billable": null,
    "is_billable": false,
    "cur": null,
    "tags": []
  },
  {
    "id": 2354220733,
    "pid": 176309267,
    "tid": null,
    "uid": 5298429,
    "description": "Cooking & Eating",
    "start": "2022-02-03T16:45:00+01:00",
    "end": "2022-02-03T17:35:03+01:00",
    "updated": "2022-02-03T17:35:05+01:00",
    "dur": 3003000,
    "user": "Huy",
    "use_stop": true,
    "client": "Future",
    "project": "Necessary",
    "project_color": "0",
    "project_hex_color": "#0b83d9",
    "task": null,
    "billable": null,
    "is_billable": false,
    "cur": null,
    "tags": []
  },
  {
    "id": 2353908057,
    "pid": 176309267,
    "tid": null,
    "uid": 5298429,
    "description": "Organizing",
    "start": "2022-02-03T15:06:46+01:00",
    "end": "2022-02-03T16:45:00+01:00",
    "updated": "2022-02-03T17:35:03+01:00",
    "dur": 5894000,
    "user": "Huy",
    "use_stop": true,
    "client": "Future",
    "project": "Necessary",
    "project_color": "0",
    "project_hex_color": "#0b83d9",
    "task": null,
    "billable": null,
    "is_billable": false,
    "cur": null,
    "tags": []
  },
  {
    "id": 2353895086,
    "pid": 176309420,
    "tid": null,
    "uid": 5298429,
    "description": "FoE",
    "start": "2022-02-03T15:01:03+01:00",
    "end": "2022-02-03T15:06:46+01:00",
    "updated": "2022-02-03T15:06:47+01:00",
    "dur": 343000,
    "user": "Huy",
    "use_stop": true,
    "client": "Fun",
    "project": "Gaming",
    "project_color": "0",
    "project_hex_color": "#2da608",
    "task": null,
    "billable": null,
    "is_billable": false,
    "cur": null,
    "tags": []
  },
  {
    "id": 2353893801,
    "pid": 176309267,
    "tid": null,
    "uid": 5298429,
    "description": "Organizing",
    "start": "2022-02-03T14:17:48+01:00",
    "end": "2022-02-03T15:01:03+01:00",
    "updated": "2022-02-03T15:01:04+01:00",
    "dur": 2595000,
    "user": "Huy",
    "use_stop": true,
    "client": "Future",
    "project": "Necessary",
    "project_color": "0",
    "project_hex_color": "#0b83d9",
    "task": null,
    "billable": null,
    "is_billable": false,
    "cur": null,
    "tags": []
  },
  {
    "id": 2353666874,
    "pid": 177268557,
    "tid": null,
    "uid": 5298429,
    "description": "Relax",
    "start": "2022-02-03T12:52:28+01:00",
    "end": "2022-02-03T14:17:39+01:00",
    "updated": "2022-02-03T15:00:50+01:00",
    "dur": 5111000,
    "user": "Huy",
    "use_stop": true,
    "client": "Fun",
    "project": "Feel Comfortable",
    "project_color": "0",
    "project_hex_color": "#9e5bd9",
    "task": null,
    "billable": null,
    "is_billable": false,
    "cur": null,
    "tags": []
  },
  {
    "id": 2353645454,
    "pid": 176309267,
    "tid": null,
    "uid": 5298429,
    "description": "Cooking & Eating",
    "start": "2022-02-03T12:38:27+01:00",
    "end": "2022-02-03T12:52:28+01:00",
    "updated": "2022-02-03T12:52:30+01:00",
    "dur": 841000,
    "user": "Huy",
    "use_stop": true,
    "client": "Future",
    "project": "Necessary",
    "project_color": "0",
    "project_hex_color": "#0b83d9",
    "task": null,
    "billable": null,
    "is_billable": false,
    "cur": null,
    "tags": []
  },
  {
    "id": 2353616061,
    "pid": 176309420,
    "tid": null,
    "uid": 5298429,
    "description": "FoE",
    "start": "2022-02-03T12:19:06+01:00",
    "end": "2022-02-03T12:38:22+01:00",
    "updated": "2022-02-03T12:38:24+01:00",
    "dur": 1156000,
    "user": "Huy",
    "use_stop": true,
    "client": "Fun",
    "project": "Gaming",
    "project_color": "0",
    "project_hex_color": "#2da608",
    "task": null,
    "billable": null,
    "is_billable": false,
    "cur": null,
    "tags": []
  },
  {
    "id": 2353570876,
    "pid": 176309267,
    "tid": null,
    "uid": 5298429,
    "description": "Organizing",
    "start": "2022-02-03T11:30:00+01:00",
    "end": "2022-02-03T12:19:03+01:00",
    "updated": "2022-02-03T12:19:05+01:00",
    "dur": 2943000,
    "user": "Huy",
    "use_stop": true,
    "client": "Future",
    "project": "Necessary",
    "project_color": "0",
    "project_hex_color": "#0b83d9",
    "task": null,
    "billable": null,
    "is_billable": false,
    "cur": null,
    "tags": []
  },
  {
    "id": 2353451654,
    "pid": 177268557,
    "tid": null,
    "uid": 5298429,
    "description": "Relax",
    "start": "2022-02-03T10:36:25+01:00",
    "end": "2022-02-03T11:30:00+01:00",
    "updated": "2022-02-03T11:50:15+01:00",
    "dur": 3215000,
    "user": "Huy",
    "use_stop": true,
    "client": "Fun",
    "project": "Feel Comfortable",
    "project_color": "0",
    "project_hex_color": "#9e5bd9",
    "task": null,
    "billable": null,
    "is_billable": false,
    "cur": null,
    "tags": []
  },
  {
    "id": 2353450894,
    "pid": 176309103,
    "tid": null,
    "uid": 5298429,
    "description": "Sleep",
    "start": "2022-02-03T01:30:00+01:00",
    "end": "2022-02-03T10:36:24+01:00",
    "updated": "2022-02-03T10:36:27+01:00",
    "dur": 32784000,
    "user": "Huy",
    "use_stop": true,
    "client": "Sleep",
    "project": "Sleep",
    "project_color": "0",
    "project_hex_color": "#525266",
    "task": null,
    "billable": null,
    "is_billable": false,
    "cur": null,
    "tags": []
  },
  {
    "id": 2352814382,
    "pid": 177268557,
    "tid": null,
    "uid": 5298429,
    "description": "Relax",
    "start": "2022-02-02T22:57:36+01:00",
    "end": "2022-02-03T01:30:00+01:00",
    "updated": "2022-02-03T10:36:22+01:00",
    "dur": 9144000,
    "user": "Huy",
    "use_stop": true,
    "client": "Fun",
    "project": "Feel Comfortable",
    "project_color": "0",
    "project_hex_color": "#9e5bd9",
    "task": null,
    "billable": null,
    "is_billable": false,
    "cur": null,
    "tags": []
  },
  {
    "id": 2352637521,
    "pid": 177005400,
    "tid": null,
    "uid": 5298429,
    "description": "Bouldering",
    "start": "2022-02-02T20:46:16+01:00",
    "end": "2022-02-02T22:57:34+01:00",
    "updated": "2022-02-02T22:57:36+01:00",
    "dur": 7878000,
    "user": "Huy",
    "use_stop": true,
    "client": "Fun",
    "project": "Exercise",
    "project_color": "0",
    "project_hex_color": "#c7af14",
    "task": null,
    "billable": null,
    "is_billable": false,
    "cur": null,
    "tags": []
  },
  {
    "id": 2352498169,
    "pid": 177268557,
    "tid": null,
    "uid": 5298429,
    "description": "Relax",
    "start": "2022-02-02T19:13:37+01:00",
    "end": "2022-02-02T20:46:15+01:00",
    "updated": "2022-02-02T20:46:17+01:00",
    "dur": 5558000,
    "user": "Huy",
    "use_stop": true,
    "client": "Fun",
    "project": "Feel Comfortable",
    "project_color": "0",
    "project_hex_color": "#9e5bd9",
    "task": null,
    "billable": null,
    "is_billable": false,
    "cur": null,
    "tags": []
  },
  {
    "id": 2352396350,
    "pid": 176309267,
    "tid": null,
    "uid": 5298429,
    "description": "Grocery shopping",
    "start": "2022-02-02T18:12:54+01:00",
    "end": "2022-02-02T19:13:36+01:00",
    "updated": "2022-02-02T19:13:39+01:00",
    "dur": 3642000,
    "user": "Huy",
    "use_stop": true,
    "client": "Future",
    "project": "Necessary",
    "project_color": "0",
    "project_hex_color": "#0b83d9",
    "task": null,
    "billable": null,
    "is_billable": false,
    "cur": null,
    "tags": []
  },
  {
    "id": 2352379979,
    "pid": 176309267,
    "tid": null,
    "uid": 5298429,
    "description": "Organizing",
    "start": "2022-02-02T18:04:04+01:00",
    "end": "2022-02-02T18:12:53+01:00",
    "updated": "2022-02-02T18:12:55+01:00",
    "dur": 529000,
    "user": "Huy",
    "use_stop": true,
    "client": "Future",
    "project": "Necessary",
    "project_color": "0",
    "project_hex_color": "#0b83d9",
    "task": null,
    "billable": null,
    "is_billable": false,
    "cur": null,
    "tags": []
  },
  {
    "id": 2351786552,
    "pid": 177268557,
    "tid": null,
    "uid": 5298429,
    "description": "Relax",
    "start": "2022-02-02T13:12:45+01:00",
    "end": "2022-02-02T18:04:04+01:00",
    "updated": "2022-02-02T18:04:06+01:00",
    "dur": 17479000,
    "user": "Huy",
    "use_stop": true,
    "client": "Fun",
    "project": "Feel Comfortable",
    "project_color": "0",
    "project_hex_color": "#9e5bd9",
    "task": null,
    "billable": null,
    "is_billable": false,
    "cur": null,
    "tags": []
  },
  {
    "id": 2351704228,
    "pid": 176309267,
    "tid": null,
    "uid": 5298429,
    "description": "Organizing",
    "start": "2022-02-02T12:22:03+01:00",
    "end": "2022-02-02T13:12:45+01:00",
    "updated": "2022-02-02T13:12:47+01:00",
    "dur": 3042000,
    "user": "Huy",
    "use_stop": true,
    "client": "Future",
    "project": "Necessary",
    "project_color": "0",
    "project_hex_color": "#0b83d9",
    "task": null,
    "billable": null,
    "is_billable": false,
    "cur": null,
    "tags": []
  },
  {
    "id": 2351619321,
    "pid": 176309651,
    "tid": null,
    "uid": 5298429,
    "description": "Friends",
    "start": "2022-02-02T11:28:55+01:00",
    "end": "2022-02-02T12:22:02+01:00",
    "updated": "2022-02-02T12:22:04+01:00",
    "dur": 3187000,
    "user": "Huy",
    "use_stop": true,
    "client": "Fun",
    "project": "Relationships",
    "project_color": "0",
    "project_hex_color": "#d94182",
    "task": null,
    "billable": null,
    "is_billable": false,
    "cur": null,
    "tags": []
  },
  {
    "id": 2351574157,
    "pid": 176309267,
    "tid": null,
    "uid": 5298429,
    "description": "Cooking & Eating",
    "start": "2022-02-02T11:03:24+01:00",
    "end": "2022-02-02T11:28:52+01:00",
    "updated": "2022-02-02T11:28:54+01:00",
    "dur": 1528000,
    "user": "Huy",
    "use_stop": true,
    "client": "Future",
    "project": "Necessary",
    "project_color": "0",
    "project_hex_color": "#0b83d9",
    "task": null,
    "billable": null,
    "is_billable": false,
    "cur": null,
    "tags": []
  },
  {
    "id": 2351547769,
    "pid": 176465049,
    "tid": null,
    "uid": 5298429,
    "description": "Finances",
    "start": "2022-02-02T10:48:21+01:00",
    "end": "2022-02-02T11:03:20+01:00",
    "updated": "2022-02-02T11:03:22+01:00",
    "dur": 899000,
    "user": "Huy",
    "use_stop": true,
    "client": "Future",
    "project": "Organization",
    "project_color": "0",
    "project_hex_color": "#9e5bd9",
    "task": null,
    "billable": null,
    "is_billable": false,
    "cur": null,
    "tags": []
  },
  {
    "id": 2351546565,
    "pid": 176309267,
    "tid": null,
    "uid": 5298429,
    "description": "Organizing",
    "start": "2022-02-02T09:50:10+01:00",
    "end": "2022-02-02T10:48:11+01:00",
    "updated": "2022-02-02T10:48:13+01:00",
    "dur": 3481000,
    "user": "Huy",
    "use_stop": true,
    "client": "Future",
    "project": "Necessary",
    "project_color": "0",
    "project_hex_color": "#0b83d9",
    "task": null,
    "billable": null,
    "is_billable": false,
    "cur": null,
    "tags": []
  },
  {
    "id": 2351545357,
    "pid": 176309103,
    "tid": null,
    "uid": 5298429,
    "description": "Sleep",
    "start": "2022-02-02T01:57:17+01:00",
    "end": "2022-02-02T09:49:53+01:00",
    "updated": "2022-02-02T10:47:22+01:00",
    "dur": 28356000,
    "user": "Huy",
    "use_stop": true,
    "client": "Sleep",
    "project": "Sleep",
    "project_color": "0",
    "project_hex_color": "#525266",
    "task": null,
    "billable": null,
    "is_billable": false,
    "cur": null,
    "tags": []
  },
  {
    "id": 2351030784,
    "pid": 177268557,
    "tid": null,
    "uid": 5298429,
    "description": "Relax",
    "start": "2022-02-02T00:00:00+01:00",
    "end": "2022-02-02T01:57:03+01:00",
    "updated": "2022-02-02T10:46:59+01:00",
    "dur": 7023000,
    "user": "Huy",
    "use_stop": true,
    "client": "Fun",
    "project": "Feel Comfortable",
    "project_color": "0",
    "project_hex_color": "#9e5bd9",
    "task": null,
    "billable": null,
    "is_billable": false,
    "cur": null,
    "tags": []
  },
  {
    "id": 2350923430,
    "pid": 176309267,
    "tid": null,
    "uid": 5298429,
    "description": "Cooking & Eating",
    "start": "2022-02-01T23:29:38+01:00",
    "end": "2022-02-02T00:00:00+01:00",
    "updated": "2022-02-02T01:27:55+01:00",
    "dur": 1822000,
    "user": "Huy",
    "use_stop": true,
    "client": "Future",
    "project": "Necessary",
    "project_color": "0",
    "project_hex_color": "#0b83d9",
    "task": null,
    "billable": null,
    "is_billable": false,
    "cur": null,
    "tags": []
  },
  {
    "id": 2350475024,
    "pid": 177268557,
    "tid": null,
    "uid": 5298429,
    "description": "Relax",
    "start": "2022-02-01T18:32:50+01:00",
    "end": "2022-02-01T23:29:38+01:00",
    "updated": "2022-02-01T23:29:40+01:00",
    "dur": 17808000,
    "user": "Huy",
    "use_stop": true,
    "client": "Fun",
    "project": "Feel Comfortable",
    "project_color": "0",
    "project_hex_color": "#9e5bd9",
    "task": null,
    "billable": null,
    "is_billable": false,
    "cur": null,
    "tags": []
  },
  {
    "id": 2349835451,
    "pid": 176309267,
    "tid": null,
    "uid": 5298429,
    "description": "Organizing",
    "start": "2022-02-01T13:05:11+01:00",
    "end": "2022-02-01T18:32:50+01:00",
    "updated": "2022-02-01T18:32:51+01:00",
    "dur": 19659000,
    "user": "Huy",
    "use_stop": true,
    "client": "Future",
    "project": "Necessary",
    "project_color": "0",
    "project_hex_color": "#0b83d9",
    "task": null,
    "billable": null,
    "is_billable": false,
    "cur": null,
    "tags": []
  },
  {
    "id": 2349714728,
    "pid": 176309267,
    "tid": null,
    "uid": 5298429,
    "description": "Morning Routine",
    "start": "2022-02-01T12:21:52+01:00",
    "end": "2022-02-01T13:05:11+01:00",
    "updated": "2022-02-01T13:33:36+01:00",
    "dur": 2599000,
    "user": "Huy",
    "use_stop": true,
    "client": "Future",
    "project": "Necessary",
    "project_color": "0",
    "project_hex_color": "#0b83d9",
    "task": null,
    "billable": null,
    "is_billable": false,
    "cur": null,
    "tags": []
  },
  {
    "id": 2349494831,
    "pid": 176309103,
    "tid": null,
    "uid": 5298429,
    "description": "lie in bed",
    "start": "2022-02-01T10:15:11+01:00",
    "end": "2022-02-01T12:21:51+01:00",
    "updated": "2022-02-01T12:21:53+01:00",
    "dur": 7600000,
    "user": "Huy",
    "use_stop": true,
    "client": "Sleep",
    "project": "Sleep",
    "project_color": "0",
    "project_hex_color": "#525266",
    "task": null,
    "billable": null,
    "is_billable": false,
    "cur": null,
    "tags": []
  },
  {
    "id": 2349492308,
    "pid": 176309103,
    "tid": null,
    "uid": 5298429,
    "description": "Sleep",
    "start": "2022-02-01T01:15:00+01:00",
    "end": "2022-02-01T10:15:10+01:00",
    "updated": "2022-02-01T10:15:12+01:00",
    "dur": 32410000,
    "user": "Huy",
    "use_stop": true,
    "client": "Sleep",
    "project": "Sleep",
    "project_color": "0",
    "project_hex_color": "#525266",
    "task": null,
    "billable": null,
    "is_billable": false,
    "cur": null,
    "tags": []
  }
]